SPrettify/Prettify.py
SPrettify/__init__.py
SPrettify/__version__.py
sprettify-0.0.3.dist-info/METADATA
sprettify-0.0.3.dist-info/WHEEL
sprettify-0.0.3.dist-info/top_level.txt
sprettify-0.0.3.dist-info/RECORD
